surfkit/__init__.py
surfkit/agent.py
surfkit/auth/default.py
surfkit/auth/key.py
surfkit/auth/provider.py
surfkit/auth/transport.py
surfkit/auth/util.py
surfkit/cli/main.py
surfkit/cli/new.py
surfkit/cli/templates/agent.py
surfkit/cli/templates/agents/base.py
surfkit/cli/templates/agents/surf4v.py
surfkit/cli/templates/agents/surfskelly.py
surfkit/cli/templates/device.py
surfkit/cli/util.py
surfkit/cli/view.py
surfkit/client.py
surfkit/config.py
surfkit/db/conn.py
surfkit/db/models.py
surfkit/env.py
surfkit/env_opts.py
surfkit/hub.py
surfkit/learn/base.py
surfkit/prompt/annots.py
surfkit/runtime/agent/base.py
surfkit/runtime/agent/docker.py
surfkit/runtime/agent/hub.py
surfkit/runtime/agent/kube.py
surfkit/runtime/agent/load.py
surfkit/runtime/agent/process.py
surfkit/runtime/agent/util.py
surfkit/runtime/container/base.py
surfkit/runtime/container/docker.py
surfkit/runtime/container/kube.py
surfkit/runtime/container/load.py
surfkit/runtime/vm/base.py
surfkit/server/models.py
surfkit/server/routes.py
surfkit/skill.py
surfkit/types.py
surfkit/util.py
surfkit-0.1.427.dist-info/LICENSE
surfkit-0.1.427.dist-info/METADATA
surfkit-0.1.427.dist-info/WHEEL
surfkit-0.1.427.dist-info/entry_points.txt
surfkit-0.1.427.dist-info/RECORD
