Metadata-Version: 2.1
Name: surfkit
Version: 0.1.427
Summary: A toolkit for building AI agents that use devices
License: MIT
Author: Patrick Barker
Author-email: patrickbarkerco@gmail.com
Requires-Python: >=3.10,<4.0
Classifier: License :: OSI Approved :: MIT License
Classifier: Programming Language :: Python :: 3
Classifier: Programming Language :: Python :: 3.10
Classifier: Programming Language :: Python :: 3.11
Classifier: Programming Language :: Python :: 3.12
Requires-Dist: agentcore (>=0.1.2,<0.2.0)
Requires-Dist: agentdesk (>=0.2.136,<0.3.0)
Requires-Dist: devicebay (>=0.1.11,<0.2.0)
Requires-Dist: docker (>=7.0.0,<8.0.0)
Requires-Dist: litellm (>=1.35.8,<2.0.0)
Requires-Dist: namesgenerator (>=0.3,<0.4)
Requires-Dist: pydantic (>=2.6.4,<3.0.0)
Requires-Dist: pyyaml (>=6.0.1,<7.0.0)
Requires-Dist: rich (>=13.7.1,<14.0.0)
Requires-Dist: rootpath (>=0.1.1,<0.2.0)
Requires-Dist: taskara (>=0.1.246,<0.2.0)
Requires-Dist: toolfuse (>=0.1.15,<0.2.0)
Requires-Dist: tqdm (>=4.66.4,<5.0.0)
